KibisisUtil/__init__.py
KibisisUtil/kibisisTuil.py
KibisisUtil/kibisisUtil.py
KibisisUtilProject-0.0.2.dist-info/LICENSE
KibisisUtilProject-0.0.2.dist-info/METADATA
KibisisUtilProject-0.0.2.dist-info/WHEEL
KibisisUtilProject-0.0.2.dist-info/top_level.txt
KibisisUtilProject-0.0.2.dist-info/RECORD
