Metadata-Version: 2.1
Name: KibisisUtilProject
Version: 0.0.2
Summary: 수집을 위한 util 모음
Home-page: https://github.com/alkaline2018/KibisisUtil
Author: song
Author-email: shdth117@gmail.com
License: UNKNOWN
Platform: UNKNOWN
Classifier: License :: OSI Approved :: MIT License
License-File: LICENSE
Requires-Dist: cython
